pycspwrapper/LVStat.py
pycspwrapper/__init__.py
pycspwrapper-0.2.1.dist-info/LICENSE
pycspwrapper-0.2.1.dist-info/METADATA
pycspwrapper-0.2.1.dist-info/WHEEL
pycspwrapper-0.2.1.dist-info/top_level.txt
pycspwrapper-0.2.1.dist-info/RECORD
