Metadata-Version: 2.1
Name: pycspwrapper
Version: 0.2.1
Summary: Python wrapper for Latvian official statistics portal API: https://stat.gov.lv/en/api-and-code-list-registry.
Home-page: https://github.com/vf42/pycspwrapper
Author: Vadim Fedorov
Author-email: vadim@vf42.com
License: MIT
Classifier: License :: OSI Approved :: MIT License
Classifier: Operating System :: OS Independent
License-File: LICENSE
Requires-Dist: requests >=2.21.0
